dexray_insight/__init__.py
dexray_insight/about.py
dexray_insight/asam.py
dexray_insight/Utils/__init__.py
dexray_insight/Utils/androguardObjClass.py
dexray_insight/Utils/blobUnpack.py
dexray_insight/Utils/file_utils.py
dexray_insight/Utils/log.py
dexray_insight/apk_diffing/__init__.py
dexray_insight/apk_diffing/apk_diffing_module.py
dexray_insight/apk_overview/__init__.py
dexray_insight/apk_overview/android_manifest_desc.py
dexray_insight/apk_overview/apk.py
dexray_insight/apk_overview/app.py
dexray_insight/apk_overview/axml.py
dexray_insight/apk_overview/dvm_permissions.py
dexray_insight/apk_overview/manifest_analysis.py
dexray_insight/apk_overview/manifest_utils.py
dexray_insight/apk_overview/network_security.py
dexray_insight/apk_overview/types.py
dexray_insight/apk_overview/utils.py
dexray_insight/apk_overview/zipfile.py
dexray_insight/apk_overview/resources/__init__.py
dexray_insight/apk_overview/resources/public.py
dexray_insight/apk_overview/resources/public.xml
dexray_insight/core/__init__.py
dexray_insight/core/analysis_engine.py
dexray_insight/core/base_classes.py
dexray_insight/core/configuration.py
dexray_insight/core/security_engine.py
dexray_insight/core/temporal_directory.py
dexray_insight/manifest_analysis/__init__.py
dexray_insight/manifest_analysis/manifest_analysis_module.py
dexray_insight/modules/__init__.py
dexray_insight/modules/api_invocation_analysis.py
dexray_insight/modules/apk_overview_analysis.py
dexray_insight/modules/dotnet_analysis.py
dexray_insight/modules/library_detection.py
dexray_insight/modules/manifest_analysis.py
dexray_insight/modules/permission_analysis.py
dexray_insight/modules/signature_analysis.py
dexray_insight/modules/behaviour_analysis/__init__.py
dexray_insight/modules/behaviour_analysis/behaviour_analysis_module.py
dexray_insight/modules/behaviour_analysis/analyzers/__init__.py
dexray_insight/modules/behaviour_analysis/analyzers/device_analyzer.py
dexray_insight/modules/behaviour_analysis/analyzers/media_analyzer.py
dexray_insight-1.0.0.3.dist-info/licenses/LICENSE
dexray_insight-1.0.0.3.dist-info/METADATA
dexray_insight-1.0.0.3.dist-info/WHEEL
dexray_insight-1.0.0.3.dist-info/entry_points.txt
dexray_insight-1.0.0.3.dist-info/top_level.txt
dexray_insight-1.0.0.3.dist-info/RECORD
