Metadata-Version: 2.4
Name: dexray-insight
Version: 1.0.0.3
Summary: This project is part of the dynamic Sandbox Sandroid. Its purpose is to do static analysis to grasp a basic understanding of an Android application. It also allows security analysis of an APK.
Author: Daniel Baier, Jan-Niclas Hilgert, Jannis Finn Borg-Olivier
License: GPL-3.0
Project-URL: Homepage, https://github.com/fkie-cad/Sandroid_Dexray-Insight
Project-URL: Repository, https://github.com/fkie-cad/Sandroid_Dexray-Insight
Project-URL: Issues, https://github.com/fkie-cad/Sandroid_Dexray-Insight/issues
Keywords: mobile,static analysis,apk,malware,android
Classifier: License :: OSI Approved :: GNU General Public License v3 (GPLv3)
Classifier: Operating System :: OS Independent
Classifier: Natural Language :: English
Classifier: Programming Language :: Python :: 3 :: Only
Classifier: Programming Language :: Python :: 3.11
Classifier: Programming Language :: Python :: 3.12
Classifier: Programming Language :: Python :: 3.13
Classifier: Topic :: Security
Classifier: Topic :: Software Development :: Debuggers
Classifier: Development Status :: 4 - Beta
Classifier: Intended Audience :: Developers
Classifier: Intended Audience :: Information Technology
Requires-Python: >=3.11
License-File: LICENSE
Requires-Dist: androguard>=3.4.0
Requires-Dist: lxml
Requires-Dist: requests
Requires-Dist: pyyaml
Requires-Dist: colorama
Requires-Dist: tqdm
Requires-Dist: lz4
Requires-Dist: xxhash
Requires-Dist: bs4
Requires-Dist: kavanoz
Requires-Dist: python-magic
Requires-Dist: r2pipe
Provides-Extra: test
Requires-Dist: pytest>=7.4.0; extra == "test"
Requires-Dist: pytest-mock>=3.11.1; extra == "test"
Requires-Dist: pytest-cov>=4.1.0; extra == "test"
Requires-Dist: pytest-benchmark>=4.0.0; extra == "test"
Requires-Dist: pytest-xdist>=3.3.1; extra == "test"
Requires-Dist: pytest-timeout>=2.1.0; extra == "test"
Requires-Dist: pytest-asyncio>=0.21.1; extra == "test"
Requires-Dist: factory-boy>=3.3.0; extra == "test"
Requires-Dist: responses>=0.23.0; extra == "test"
Requires-Dist: freezegun>=1.2.2; extra == "test"
Requires-Dist: zipfile36>=0.1.3; extra == "test"
Provides-Extra: dev
Requires-Dist: black>=23.7.0; extra == "dev"
Requires-Dist: flake8>=6.0.0; extra == "dev"
Requires-Dist: mypy>=1.5.0; extra == "dev"
Requires-Dist: radon>=5.1.0; extra == "dev"
Requires-Dist: pytest>=7.4.0; extra == "dev"
Requires-Dist: pytest-mock>=3.11.1; extra == "dev"
Requires-Dist: pytest-cov>=4.1.0; extra == "dev"
Requires-Dist: pytest-benchmark>=4.0.0; extra == "dev"
Requires-Dist: pytest-xdist>=3.3.1; extra == "dev"
Requires-Dist: pytest-timeout>=2.1.0; extra == "dev"
Requires-Dist: pytest-asyncio>=0.21.1; extra == "dev"
Requires-Dist: factory-boy>=3.3.0; extra == "dev"
Requires-Dist: responses>=0.23.0; extra == "dev"
Requires-Dist: freezegun>=1.2.2; extra == "dev"
Requires-Dist: zipfile36>=0.1.3; extra == "dev"
Provides-Extra: yara
Requires-Dist: apkid; extra == "yara"
Dynamic: license-file
